<HBProfile>
  <Name></Name>
  <MinDurability>0.4</MinDurability>
  <MinFreeBagSlots>1</MinFreeBagSlots>
  
  <MinLevel>1</MinLevel>
  <MaxLevel>86</MaxLevel>
  <Factions>99999</Factions>
  
  <MailGrey>False</MailGrey>
  <MailWhite>True</MailWhite>
  <MailGreen>True</MailGreen>
  <MailBlue>True</MailBlue>
  <MailPurple>True</MailPurple>
 
  <SellGrey>True</SellGrey>
  <SellWhite>True</SellWhite>
  <SellGreen>False</SellGreen>
  <SellBlue>False</SellBlue>
  <SellPurple>False</SellPurple>

	<Vendors>

	</Vendors>
	
	<Mailboxes>

	</Mailboxes>

  <Hotspots>
    <Hotspot X="-9548.593" Y="-3785.528" Z="238.5452" />
    <Hotspot X="-9455.573" Y="-3707.531" Z="270.9995" />
    <Hotspot X="-9476.066" Y="-3579.579" Z="276.2826" />
    <Hotspot X="-9582.416" Y="-3491.386" Z="263.978" />
    <Hotspot X="-9639.748" Y="-3370.535" Z="249.3511" />
    <Hotspot X="-9746.952" Y="-3292.943" Z="214.1271" />
    <Hotspot X="-9804.243" Y="-3178.775" Z="201.7658" />
    <Hotspot X="-9723.56" Y="-3072.657" Z="194.539" />
    <Hotspot X="-9720.858" Y="-2934.815" Z="197.3423" />
    <Hotspot X="-9723.401" Y="-2797.376" Z="185.5581" />
    <Hotspot X="-9724.408" Y="-2658.531" Z="187.5658" />
    <Hotspot X="-9725.336" Y="-2520.49" Z="190.2168" />
    <Hotspot X="-9726.473" Y="-2381.739" Z="192.8818" />
    <Hotspot X="-9750.552" Y="-2244.761" Z="195.5527" />
    <Hotspot X="-9715.943" Y="-2114.394" Z="198.2157" />
    <Hotspot X="-9708.38" Y="-1985.536" Z="200.8642" />
    <Hotspot X="-9831.35" Y="-1923.744" Z="203.547" />
    <Hotspot X="-9928.695" Y="-1945.556" Z="206.2239" />
    <Hotspot X="-9904.563" Y="-1809.773" Z="208.9147" />
    <Hotspot X="-9813.042" Y="-1774.77" Z="165.3213" />
    <Hotspot X="-9675.731" Y="-1788.136" Z="174.3418" />
    <Hotspot X="-9552.794" Y="-1850.364" Z="193.333" />
    <Hotspot X="-9420.781" Y="-1862.506" Z="205.8435" />
    <Hotspot X="-9292.804" Y="-1906.649" Z="205.2979" />
    <Hotspot X="-9173.702" Y="-1975.823" Z="204.4461" />
    <Hotspot X="-9040.434" Y="-2006.016" Z="223.8308" />
    <Hotspot X="-8994.155" Y="-2023.521" Z="229.2006" />
    <Hotspot X="-8927.558" Y="-2061.755" Z="241.5081" />
    <Hotspot X="-8866.296" Y="-2147.096" Z="257.121" />
    <Hotspot X="-8865.957" Y="-2171.153" Z="247.3842" />
    <Hotspot X="-8806.046" Y="-2209.119" Z="275.0539" />
    <Hotspot X="-8775.902" Y="-2307.554" Z="291.3227" />
    <Hotspot X="-8692.729" Y="-2292.989" Z="283.2693" />
    <Hotspot X="-8681.991" Y="-2315.271" Z="273.5754" />
    <Hotspot X="-8758.935" Y="-2426.192" Z="245.6849" />
    <Hotspot X="-8748.621" Y="-2559.041" Z="236.0301" />
    <Hotspot X="-8753.674" Y="-2691.932" Z="268.6935" />
    <Hotspot X="-8806.053" Y="-2809.575" Z="320.889" />
    <Hotspot X="-8851.375" Y="-2935.504" Z="348.782" />
    <Hotspot X="-8807.484" Y="-3065.43" Z="354.8014" />
    <Hotspot X="-8853.035" Y="-3158.071" Z="342.9155" />
    <Hotspot X="-8920.955" Y="-3255.116" Z="294.1666" />
    <Hotspot X="-8967.659" Y="-3385.22" Z="287.3007" />
    <Hotspot X="-9029.753" Y="-3507.137" Z="298.5495" />
    <Hotspot X="-9163.108" Y="-3540.687" Z="306.5092" />
    <Hotspot X="-9299.535" Y="-3561.621" Z="297.8768" />
    <Hotspot X="-9417.335" Y="-3507.445" Z="267.1479" />
    <Hotspot X="-9508.925" Y="-3410.613" Z="227.0296" />
    <Hotspot X="-9586.896" Y="-3302.433" Z="189.6675" />
    <Hotspot X="-9646.693" Y="-3181.469" Z="206.7659" />
    <Hotspot X="-9665.848" Y="-3047.672" Z="226.2217" />
    <Hotspot X="-9650.457" Y="-2912.93" Z="214.5109" />
    <Hotspot X="-9642.359" Y="-2775.84" Z="198.7175" />
    <Hotspot X="-9644.229" Y="-2638.024" Z="186.1174" />
    <Hotspot X="-9653.34" Y="-2499.701" Z="172.8468" />
    <Hotspot X="-9659.065" Y="-2363.638" Z="166.9014" />
    <Hotspot X="-9664.901" Y="-2224.962" Z="160.8419" />
    <Hotspot X="-9670.557" Y="-2090.583" Z="154.9701" />
    <Hotspot X="-9653.766" Y="-1956.243" Z="173.6327" />
    <Hotspot X="-9531.732" Y="-1917.924" Z="199.2555" />
    <Hotspot X="-9395.134" Y="-1922.961" Z="211.7816" />
    <Hotspot X="-9277.924" Y="-1994.637" Z="200.0728" />
    <Hotspot X="-9166.547" Y="-2076.131" Z="214.5778" />
    <Hotspot X="-9063.864" Y="-2164.278" Z="236.5871" />
    <Hotspot X="-8980.648" Y="-2272.873" Z="258.8441" />
    <Hotspot X="-8919.173" Y="-2395.048" Z="280.9965" />
    <Hotspot X="-8937.791" Y="-2521.989" Z="303.1489" />
    <Hotspot X="-9016.504" Y="-2622.249" Z="250.7456" />
    <Hotspot X="-9102.746" Y="-2720.151" Z="208.6085" />
    <Hotspot X="-9176.021" Y="-2807.992" Z="186.086" />
    <Hotspot X="-9150.117" Y="-2942.923" Z="205.4362" />
    <Hotspot X="-9124.771" Y="-3077.334" Z="218.7471" />
    <Hotspot X="-9091.554" Y="-3211.544" Z="214.0756" />
    <Hotspot X="-9050.048" Y="-3264.625" Z="233.8706" />
    <Hotspot X="-9181.136" Y="-3305.709" Z="221.6025" />
    <Hotspot X="-9309.532" Y="-3354.89" Z="204.0804" />
    <Hotspot X="-9428.796" Y="-3346.715" Z="186.6028" />
    <Hotspot X="-9533.424" Y="-3270.915" Z="165.8787" />
    <Hotspot X="-9577.245" Y="-3145.585" Z="141.0396" />
    <Hotspot X="-9571.254" Y="-3007.708" Z="148.6927" />
    <Hotspot X="-9547.476" Y="-2875.96" Z="152.8296" />
    <Hotspot X="-9447.575" Y="-2808.241" Z="167.5947" />
    <Hotspot X="-9512.421" Y="-2780.564" Z="153.8587" />
    <Hotspot X="-9455.772" Y="-2862.692" Z="154.4267" />
    <Hotspot X="-9489.979" Y="-2843.692" Z="155.2579" />
    <Hotspot X="-9539.035" Y="-2806.593" Z="149.8963" />
    <Hotspot X="-9583.696" Y="-2676.535" Z="146.1858" />
    <Hotspot X="-9565.002" Y="-2541.244" Z="139.6765" />
    <Hotspot X="-9580.712" Y="-2405.928" Z="152.566" />
    <Hotspot X="-9614.219" Y="-2274.435" Z="176.7645" />
    <Hotspot X="-9622.831" Y="-2139.771" Z="191.9203" />
    <Hotspot X="-9523.179" Y="-2050.52" Z="188.1827" />
    <Hotspot X="-9389.545" Y="-2014.821" Z="189.5336" />
    <Hotspot X="-9274.254" Y="-2025.427" Z="209.3392" />
    <Hotspot X="-9261.772" Y="-2136.952" Z="194.1651" />
    <Hotspot X="-9262.732" Y="-2270.18" Z="180.6235" />
    <Hotspot X="-9185.993" Y="-2383.594" Z="181.9783" />
    <Hotspot X="-9150.961" Y="-2514.642" Z="189.7264" />
    <Hotspot X="-9177.859" Y="-2649.896" Z="182.391" />
    <Hotspot X="-9192.156" Y="-2787.411" Z="180.7072" />
    <Hotspot X="-9206.41" Y="-2921.731" Z="207.0351" />
    <Hotspot X="-9226.071" Y="-3054.721" Z="233.3581" />
    <Hotspot X="-9247.375" Y="-3191.733" Z="228.2148" />
    <Hotspot X="-9258.637" Y="-3303.61" Z="220.1934" />
    <Hotspot X="-9287.331" Y="-3296.73" Z="212.5297" />
    <Hotspot X="-9381.889" Y="-3311.415" Z="209.3455" />
    <Hotspot X="-9455.21" Y="-3205.236" Z="193.1241" />
    <Hotspot X="-9545.749" Y="-3116.192" Z="162.9465" />
    <Hotspot X="-9540.912" Y="-2980.766" Z="158.3449" />
    <Hotspot X="-9475.661" Y="-2868.838" Z="156.7742" />
    <Hotspot X="-9461.538" Y="-2850.935" Z="158.6849" />
    <Hotspot X="-9475.693" Y="-2831.955" Z="159.1128" />
    <Hotspot X="-9510.494" Y="-2698.356" Z="165.0108" />
    <Hotspot X="-9522.314" Y="-2563.366" Z="159.5188" />
    <Hotspot X="-9483.69" Y="-2433.986" Z="155.1227" />
    <Hotspot X="-9464.219" Y="-2295.777" Z="141.3306" />
    <Hotspot X="-9408.283" Y="-2169.804" Z="148.4097" />
    <Hotspot X="-9349.028" Y="-2237.314" Z="175.8027" />
    <Hotspot X="-9320.299" Y="-2371.339" Z="172.8882" />
    <Hotspot X="-9223.996" Y="-2465.419" Z="176.3465" />
    <Hotspot X="-9256.931" Y="-2587.799" Z="172.3269" />
    <Hotspot X="-9235.007" Y="-2723.336" Z="179.7855" />
    <Hotspot X="-9282.024" Y="-2851.168" Z="205.9857" />
    <Hotspot X="-9326.322" Y="-2978.022" Z="240.3472" />
    <Hotspot X="-9389.654" Y="-3081.607" Z="275.2463" />
    <Hotspot X="-9357.964" Y="-3089.493" Z="310.1802" />
    <Hotspot X="-9422.164" Y="-3169.275" Z="271.7702" />
    <Hotspot X="-9501.447" Y="-3110.502" Z="223.4814" />
    <Hotspot X="-9381.787" Y="-3165.155" Z="227.3375" />
    <Hotspot X="-9283.945" Y="-3082.377" Z="221.9673" />
    <Hotspot X="-9250.576" Y="-2949.656" Z="216.6777" />
    <Hotspot X="-9304.38" Y="-2837.14" Z="211.3392" />
    <Hotspot X="-9402.91" Y="-2759.961" Z="155.9698" />
    <Hotspot X="-9436.281" Y="-2640.089" Z="125.5883" />
    <Hotspot X="-9392.575" Y="-2508.942" Z="131.7849" />
    <Hotspot X="-9362.874" Y="-2375.562" Z="146.2241" />
    <Hotspot X="-9353.135" Y="-2240.108" Z="171.5165" />
    <Hotspot X="-9351.304" Y="-2104.289" Z="196.8972" />
    <Hotspot X="-9441.741" Y="-2008.21" Z="222.2653" />
    <Hotspot X="-9547.107" Y="-1922.978" Z="247.646" />
    <Hotspot X="-9603.982" Y="-1813.757" Z="245.3586" />
    <Hotspot X="-9608.247" Y="-1704.084" Z="208.6383" />
    <Hotspot X="-9604.989" Y="-1748.514" Z="220.7341" />
    <Hotspot X="-9593.066" Y="-1873.279" Z="260.2701" />
    <Hotspot X="-9498.191" Y="-1970.08" Z="234.9525" />
    <Hotspot X="-9385.848" Y="-2047.417" Z="209.534" />
    <Hotspot X="-9348.232" Y="-2171.925" Z="184.2478" />
    <Hotspot X="-9358.008" Y="-2307.886" Z="158.8608" />
    <Hotspot X="-9370.291" Y="-2443.248" Z="136.0278" />
    <Hotspot X="-9415.252" Y="-2574.122" Z="127.4038" />
    <Hotspot X="-9442.576" Y="-2707.301" Z="132.4379" />
    <Hotspot X="-9354.152" Y="-2798.144" Z="184.3142" />
    <Hotspot X="-9253.342" Y="-2882.53" Z="213.9979" />
    <Hotspot X="-9271.362" Y="-3014.551" Z="219.3179" />
    <Hotspot X="-9319.012" Y="-3139.266" Z="224.6828" />
    <Hotspot X="-9437.403" Y="-3125.231" Z="230.4528" />
    <Hotspot X="-9481.295" Y="-3163.894" Z="238.4386" />
    <Hotspot X="-9375.479" Y="-3149.648" Z="318.0206" />
    <Hotspot X="-9386.714" Y="-3039.052" Z="292.8001" />
    <Hotspot X="-9346.713" Y="-3042.252" Z="257.9009" />
    <Hotspot X="-9305.721" Y="-2914.376" Z="222.0684" />
    <Hotspot X="-9257.653" Y="-2787.638" Z="189.7752" />
    <Hotspot X="-9242.754" Y="-2656.726" Z="177.1433" />
    <Hotspot X="-9225.298" Y="-2527.659" Z="175.741" />
    <Hotspot X="-9279.505" Y="-2425.101" Z="173.2225" />
    <Hotspot X="-9342.609" Y="-2305.896" Z="174.0852" />
    <Hotspot X="-9360.788" Y="-2170.138" Z="164.0639" />
    <Hotspot X="-9438.546" Y="-2231.697" Z="145.1308" />
    <Hotspot X="-9478.954" Y="-2362.425" Z="147.3461" />
    <Hotspot X="-9500.061" Y="-2498.387" Z="153.6033" />
    <Hotspot X="-9525.207" Y="-2630.947" Z="167.7822" />
    <Hotspot X="-9495.664" Y="-2766.304" Z="162.2173" />
    <Hotspot X="-9458.805" Y="-2846.831" Z="158.5295" />
    <Hotspot X="-9464.969" Y="-2851.433" Z="158.3998" />
    <Hotspot X="-9506.136" Y="-2927.723" Z="156.8391" />
    <Hotspot X="-9554.173" Y="-3047.223" Z="156.3886" />
    <Hotspot X="-9500.548" Y="-3157.367" Z="181.2264" />
    <Hotspot X="-9431.725" Y="-3270.302" Z="198.5701" />
    <Hotspot X="-9314.198" Y="-3320.908" Z="210.8707" />
    <Hotspot X="-9282.01" Y="-3312.506" Z="215.8719" />
    <Hotspot X="-9254.864" Y="-3260.601" Z="222.8717" />
    <Hotspot X="-9236.79" Y="-3123.658" Z="230.8611" />
    <Hotspot X="-9216.701" Y="-2987" Z="226.025" />
    <Hotspot X="-9198.879" Y="-2855.626" Z="186.3578" />
    <Hotspot X="-9186.626" Y="-2718.114" Z="179.6294" />
    <Hotspot X="-9161.301" Y="-2582.647" Z="190.4072" />
    <Hotspot X="-9156.158" Y="-2445.57" Z="185.8485" />
    <Hotspot X="-9220.915" Y="-2324.395" Z="178.0508" />
    <Hotspot X="-9274.522" Y="-2205.317" Z="187.6188" />
    <Hotspot X="-9244.488" Y="-2078.358" Z="215.4638" />
    <Hotspot X="-9321.726" Y="-2015.59" Z="201.6471" />
    <Hotspot X="-9457.136" Y="-2030.763" Z="187.5933" />
    <Hotspot X="-9582.353" Y="-2086.23" Z="189.8714" />
    <Hotspot X="-9631.556" Y="-2208.519" Z="187.8158" />
    <Hotspot X="-9593.93" Y="-2339.325" Z="164.9542" />
    <Hotspot X="-9565.686" Y="-2472.702" Z="143.8943" />
    <Hotspot X="-9579.253" Y="-2608.887" Z="141.0746" />
    <Hotspot X="-9565.488" Y="-2743.356" Z="147.2665" />
    <Hotspot X="-9500.233" Y="-2835.195" Z="153.9911" />
    <Hotspot X="-9474.607" Y="-2867.745" Z="155.6751" />
    <Hotspot X="-9466.141" Y="-2828.485" Z="151.2001" />
    <Hotspot X="-9510.248" Y="-2803.073" Z="177.4037" />
    <Hotspot X="-9483.707" Y="-2851.486" Z="157.737" />
    <Hotspot X="-9565.827" Y="-2938.215" Z="153.2433" />
    <Hotspot X="-9574.827" Y="-3076.154" Z="143.8908" />
    <Hotspot X="-9564.013" Y="-3212.261" Z="151.3166" />
    <Hotspot X="-9468.215" Y="-3292.052" Z="177.4011" />
    <Hotspot X="-9373.469" Y="-3379.832" Z="195.289" />
    <Hotspot X="-9245.469" Y="-3329.898" Z="212.8892" />
    <Hotspot X="-9113.896" Y="-3290.55" Z="228.3009" />
    <Hotspot X="-9033.166" Y="-3221.812" Z="228.3152" />
    <Hotspot X="-9109.729" Y="-3144.662" Z="212.4775" />
    <Hotspot X="-9137.393" Y="-3010.039" Z="215.037" />
    <Hotspot X="-9162.944" Y="-2875.271" Z="195.7586" />
    <Hotspot X="-9162.846" Y="-2746.62" Z="189.5145" />
    <Hotspot X="-9057.256" Y="-2673.786" Z="227.3574" />
    <Hotspot X="-8975.815" Y="-2572.781" Z="276.8192" />
    <Hotspot X="-8909.553" Y="-2459.915" Z="291.9929" />
    <Hotspot X="-8949.872" Y="-2334.036" Z="269.9341" />
    <Hotspot X="-9019.616" Y="-2216.619" Z="247.688" />
    <Hotspot X="-9112.624" Y="-2117.717" Z="225.6072" />
    <Hotspot X="-9221.788" Y="-2033.527" Z="203.2786" />
    <Hotspot X="-9336.586" Y="-1957.589" Z="203.4861" />
    <Hotspot X="-9463.713" Y="-1915.757" Z="212.1148" />
    <Hotspot X="-9598.707" Y="-1918.114" Z="186.5368" />
    <Hotspot X="-9668.828" Y="-2021.169" Z="160.799" />
    <Hotspot X="-9667.818" Y="-2155.658" Z="157.8136" />
    <Hotspot X="-9661.988" Y="-2294.197" Z="163.8672" />
    <Hotspot X="-9656.264" Y="-2430.226" Z="169.811" />
    <Hotspot X="-9649.881" Y="-2570.327" Z="176.3499" />
    <Hotspot X="-9642.489" Y="-2706.869" Z="192.8048" />
    <Hotspot X="-9643.391" Y="-2844.594" Z="204.21" />
    <Hotspot X="-9658.516" Y="-2980.456" Z="229.5813" />
    <Hotspot X="-9670.356" Y="-3116.065" Z="216.5537" />
    <Hotspot X="-9620.591" Y="-3243.324" Z="193.424" />
    <Hotspot X="-9547.988" Y="-3356.972" Z="206.8892" />
    <Hotspot X="-9463.217" Y="-3459.284" Z="247.1284" />
    <Hotspot X="-9366.125" Y="-3548.619" Z="286.2131" />
    <Hotspot X="-9231.241" Y="-3551.569" Z="306.2778" />
    <Hotspot X="-9094.906" Y="-3528.604" Z="302.9825" />
    <Hotspot X="-8992.272" Y="-3450.133" Z="293.1915" />
    <Hotspot X="-8943.138" Y="-3320.09" Z="286.7058" />
    <Hotspot X="-8906.584" Y="-3190.922" Z="315.9578" />
    <Hotspot X="-8792.99" Y="-3127.856" Z="354.3193" />
    <Hotspot X="-8836.36" Y="-3002.349" Z="351.4683" />
    <Hotspot X="-8832.083" Y="-2869.874" Z="342.4702" />
    <Hotspot X="-8778.797" Y="-2751.367" Z="294.9145" />
    <Hotspot X="-8742.821" Y="-2627.554" Z="246.4609" />
    <Hotspot X="-8765.659" Y="-2491.916" Z="235.3353" />
    <Hotspot X="-8724.13" Y="-2368.505" Z="261.026" />
    <Hotspot X="-8669.282" Y="-2269.039" Z="278.3813" />
    <Hotspot X="-8717.02" Y="-2320.091" Z="284.9062" />
    <Hotspot X="-8788.266" Y="-2273.519" Z="292.6388" />
    <Hotspot X="-8854.646" Y="-2174.074" Z="250.9938" />
    <Hotspot X="-8859.663" Y="-2151.717" Z="254.587" />
    <Hotspot X="-8912.275" Y="-2118.073" Z="246.359" />
    <Hotspot X="-8961.494" Y="-2038.793" Z="234.6074" />
    <Hotspot X="-9004.23" Y="-2012.183" Z="230.2832" />
    <Hotspot X="-9107.779" Y="-1994.764" Z="212.6461" />
    <Hotspot X="-9235.362" Y="-1944.675" Z="202.6567" />
    <Hotspot X="-9351.527" Y="-1870.038" Z="213.3248" />
    <Hotspot X="-9487.826" Y="-1871.484" Z="197.9025" />
    <Hotspot X="-9615.959" Y="-1820.249" Z="181.4343" />
    <Hotspot X="-9744.37" Y="-1781.305" Z="169.7614" />
    <Hotspot X="-9881.444" Y="-1764.755" Z="171.2816" />
    <Hotspot X="-9918.35" Y="-1877.091" Z="207.5802" />
    <Hotspot X="-9882.695" Y="-1966.296" Z="204.8907" />
    <Hotspot X="-9768.817" Y="-1948.451" Z="202.2271" />
    <Hotspot X="-9696.252" Y="-2048.519" Z="199.5462" />
    <Hotspot X="-9744.759" Y="-2177.36" Z="196.8859" />
    <Hotspot X="-9738.479" Y="-2313.437" Z="194.2137" />
    <Hotspot X="-9725.803" Y="-2450.936" Z="191.5526" />
    <Hotspot X="-9724.871" Y="-2589.7" Z="188.8877" />
    <Hotspot X="-9723.943" Y="-2727.776" Z="186.2359" />
    <Hotspot X="-9722.124" Y="-2866.439" Z="191.4796" />
    <Hotspot X="-9719.969" Y="-3003.911" Z="202.748" />
    <Hotspot X="-9755.218" Y="-3131.259" Z="196.403" />
    <Hotspot X="-9792.999" Y="-3241.852" Z="207.1152" />
    <Hotspot X="-9690.342" Y="-3329.561" Z="228.2577" />
    <Hotspot X="-9620" Y="-3435.822" Z="257.8969" />
    <Hotspot X="-9526.354" Y="-3530.883" Z="270.0378" />
    <Hotspot X="-9447.482" Y="-3639.286" Z="278.3146" />
    <Hotspot X="-9486.212" Y="-3766.121" Z="257.7013" />
  </Hotspots>
  <Blackspots>
  </Blackspots>
</HBProfile>
