<HBProfile>
  <Name></Name>
  <MinDurability>0.4</MinDurability>
  <MinFreeBagSlots>1</MinFreeBagSlots>
  
  <MinLevel>1</MinLevel>
  <MaxLevel>86</MaxLevel>
  <Factions>99999</Factions>
  
  <MailGrey>False</MailGrey>
  <MailWhite>True</MailWhite>
  <MailGreen>True</MailGreen>
  <MailBlue>True</MailBlue>
  <MailPurple>True</MailPurple>
 
  <SellGrey>True</SellGrey>
  <SellWhite>True</SellWhite>
  <SellGreen>False</SellGreen>
  <SellBlue>False</SellBlue>
  <SellPurple>False</SellPurple>

	<Vendors>

	</Vendors>
	
	<Mailboxes>

	</Mailboxes>

  <Hotspots>
    <Hotspot X="-5487.277" Y="-2250.1" Z="574.455" />
    <Hotspot X="-5620.205" Y="-2228.948" Z="558.0989" />
    <Hotspot X="-5740.217" Y="-2160.046" Z="552.7896" />
    <Hotspot X="-5853.816" Y="-2083.073" Z="542.3557" />
    <Hotspot X="-5887.002" Y="-1954.011" Z="534.2581" />
    <Hotspot X="-5888.274" Y="-1816.258" Z="542.3948" />
    <Hotspot X="-5884.876" Y="-1678.013" Z="550.9421" />
    <Hotspot X="-5882.129" Y="-1539.753" Z="556.629" />
    <Hotspot X="-5889.116" Y="-1401.468" Z="549.9716" />
    <Hotspot X="-5903.795" Y="-1265.134" Z="536.72" />
    <Hotspot X="-5936.594" Y="-1131.524" Z="546.9907" />
    <Hotspot X="-5935.028" Y="-994.6002" Z="554.7741" />
    <Hotspot X="-5935.449" Y="-856.3861" Z="555.7158" />
    <Hotspot X="-5962.147" Y="-720.0726" Z="553.3838" />
    <Hotspot X="-5989.037" Y="-584.1703" Z="551.3287" />
    <Hotspot X="-6038.821" Y="-456.9551" Z="549.275" />
    <Hotspot X="-6052.464" Y="-320.5572" Z="549.0667" />
    <Hotspot X="-6069.039" Y="-183.9299" Z="558.2082" />
    <Hotspot X="-6090.774" Y="-49.83606" Z="584.319" />
    <Hotspot X="-6157.798" Y="63.10524" Z="589.5632" />
    <Hotspot X="-6254.52" Y="163.3425" Z="585.9137" />
    <Hotspot X="-6350.593" Y="262.6836" Z="582.4158" />
    <Hotspot X="-6415.783" Y="383.0387" Z="578.1295" />
    <Hotspot X="-6501.831" Y="491.335" Z="574.9785" />
    <Hotspot X="-6519.772" Y="623.1624" Z="571.8338" />
    <Hotspot X="-6471.704" Y="742.3014" Z="568.6883" />
    <Hotspot X="-6345.479" Y="797.4205" Z="565.5412" />
    <Hotspot X="-6221.325" Y="851.145" Z="562.3988" />
    <Hotspot X="-6087.813" Y="863.9883" Z="596.3727" />
    <Hotspot X="-5952.949" Y="878.5698" Z="606.5692" />
    <Hotspot X="-5827.904" Y="938.3016" Z="599.4474" />
    <Hotspot X="-5703.393" Y="996.9664" Z="586.5995" />
    <Hotspot X="-5577.855" Y="1055.284" Z="572.173" />
    <Hotspot X="-5452.814" Y="1113.371" Z="557.8036" />
    <Hotspot X="-5330.263" Y="1176.104" Z="551.8561" />
    <Hotspot X="-5223.565" Y="1259.412" Z="580.5236" />
    <Hotspot X="-5135.911" Y="1360.839" Z="590.566" />
    <Hotspot X="-5022.85" Y="1414.876" Z="604.2026" />
    <Hotspot X="-4899.662" Y="1375.464" Z="635.2987" />
    <Hotspot X="-4904.995" Y="1245.029" Z="657.7444" />
    <Hotspot X="-4869.313" Y="1123.262" Z="601.8376" />
    <Hotspot X="-4826.473" Y="992.7083" Z="586.9872" />
    <Hotspot X="-4778.548" Y="862.936" Z="586.0216" />
    <Hotspot X="-4730.75" Y="732.9669" Z="585.055" />
    <Hotspot X="-4717.764" Y="598.0037" Z="594.143" />
    <Hotspot X="-4718.973" Y="461.5731" Z="621.7775" />
    <Hotspot X="-4720.8" Y="325.814" Z="646.5499" />
    <Hotspot X="-4732.927" Y="187.4174" Z="639.701" />
    <Hotspot X="-4744.958" Y="50.12436" Z="633.3224" />
    <Hotspot X="-4757.006" Y="-87.37427" Z="626.9343" />
    <Hotspot X="-4768.724" Y="-224.951" Z="624.9266" />
    <Hotspot X="-4777.873" Y="-359.7391" Z="656.7383" />
    <Hotspot X="-4786.977" Y="-493.8585" Z="688.3922" />
    <Hotspot X="-4764.123" Y="-622.1005" Z="735.263" />
    <Hotspot X="-4734.512" Y="-746.3575" Z="788.8148" />
    <Hotspot X="-4706.348" Y="-868.432" Z="847.501" />
    <Hotspot X="-4685.604" Y="-995.7664" Z="869.2031" />
    <Hotspot X="-4669.62" Y="-1127.179" Z="828.1659" />
    <Hotspot X="-4644.708" Y="-1255.746" Z="783.4568" />
    <Hotspot X="-4611.956" Y="-1377.445" Z="739.3787" />
    <Hotspot X="-4543.416" Y="-1487.597" Z="692.0311" />
    <Hotspot X="-4468.863" Y="-1592.419" Z="644.4592" />
    <Hotspot X="-4404.262" Y="-1636.792" Z="596.9109" />
    <Hotspot X="-4520.462" Y="-1688.634" Z="623.7921" />
    <Hotspot X="-4575.399" Y="-1809.96" Z="650.4954" />
    <Hotspot X="-4619.985" Y="-1939.751" Z="672.3543" />
    <Hotspot X="-4696.399" Y="-2052.561" Z="669.6041" />
    <Hotspot X="-4783.709" Y="-2158.729" Z="658.1824" />
    <Hotspot X="-4879.496" Y="-2258.894" Z="646.581" />
    <Hotspot X="-4977.483" Y="-2316.311" Z="594.3472" />
    <Hotspot X="-5113.545" Y="-2328.494" Z="577.9372" />
    <Hotspot X="-5250.58" Y="-2344.38" Z="581.8479" />
    <Hotspot X="-5386.449" Y="-2338.385" Z="591.1008" />
    <Hotspot X="-5507.037" Y="-2331.162" Z="567.889" />
    <Hotspot X="-5596.999" Y="-2226.668" Z="556.6415" />
    <Hotspot X="-5643.931" Y="-2098.045" Z="540.1388" />
    <Hotspot X="-5671.863" Y="-1962.803" Z="529.9436" />
    <Hotspot X="-5700.905" Y="-1827.238" Z="520.9782" />
    <Hotspot X="-5729.947" Y="-1691.672" Z="512.0129" />
    <Hotspot X="-5762.946" Y="-1557.689" Z="508.3464" />
    <Hotspot X="-5804.542" Y="-1425.698" Z="515.7204" />
    <Hotspot X="-5822.456" Y="-1290.686" Z="523.1017" />
    <Hotspot X="-5802.146" Y="-1153.62" Z="530.4848" />
    <Hotspot X="-5781.83" Y="-1016.416" Z="537.8752" />
    <Hotspot X="-5796.359" Y="-879.383" Z="545.2346" />
    <Hotspot X="-5823.08" Y="-743.7721" Z="552.5994" />
    <Hotspot X="-5856.01" Y="-609.8568" Z="559.9532" />
    <Hotspot X="-5893.479" Y="-476.8853" Z="567.3144" />
    <Hotspot X="-5930.938" Y="-343.9468" Z="574.6738" />
    <Hotspot X="-5968.527" Y="-210.545" Z="582.0587" />
    <Hotspot X="-6005.977" Y="-77.63971" Z="589.4163" />
    <Hotspot X="-6043.482" Y="55.46417" Z="596.7847" />
    <Hotspot X="-6115.374" Y="172.4384" Z="604.1899" />
    <Hotspot X="-6205.001" Y="278.605" Z="611.5932" />
    <Hotspot X="-6251.767" Y="403.5349" Z="608.8849" />
    <Hotspot X="-6264.026" Y="540.4587" Z="590.5425" />
    <Hotspot X="-6259.138" Y="676.2426" Z="572.1909" />
    <Hotspot X="-6139.695" Y="713.6328" Z="568.8235" />
    <Hotspot X="-6004.609" Y="702.2675" Z="594.6196" />
    <Hotspot X="-5873.419" Y="743.5569" Z="603.46" />
    <Hotspot X="-5751.634" Y="809.934" Z="595.8127" />
    <Hotspot X="-5628.729" Y="872.6998" Z="581.7255" />
    <Hotspot X="-5505.973" Y="935.6966" Z="567.3455" />
    <Hotspot X="-5383.034" Y="998.7872" Z="552.9441" />
    <Hotspot X="-5253.858" Y="1046.613" Z="538.5499" />
    <Hotspot X="-5118.974" Y="1050.309" Z="511.9937" />
    <Hotspot X="-5003.665" Y="981.0966" Z="508.4173" />
    <Hotspot X="-4903.765" Y="885.7845" Z="511.0748" />
    <Hotspot X="-4833.951" Y="768.4371" Z="513.7361" />
    <Hotspot X="-4822.875" Y="634.5311" Z="527.322" />
    <Hotspot X="-4851.888" Y="504.7208" Z="564.3799" />
    <Hotspot X="-4883.203" Y="374.457" Z="599.0363" />
    <Hotspot X="-4902.913" Y="238.7176" Z="578.425" />
    <Hotspot X="-4896.613" Y="100.9923" Z="578.5646" />
    <Hotspot X="-4891.571" Y="-37.49226" Z="583.1367" />
    <Hotspot X="-4904.008" Y="-174.2972" Z="594.4443" />
    <Hotspot X="-4932.148" Y="-306.1364" Z="623.7639" />
    <Hotspot X="-4951.655" Y="-431.661" Z="678.4725" />
    <Hotspot X="-4971.181" Y="-557.3105" Z="733.2356" />
    <Hotspot X="-4990.893" Y="-684.1593" Z="783.3974" />
    <Hotspot X="-5007.609" Y="-821.5571" Z="780.9609" />
    <Hotspot X="-4982.973" Y="-956.7738" Z="778.1757" />
    <Hotspot X="-4984.244" Y="-1092.513" Z="775.4103" />
    <Hotspot X="-5003.167" Y="-1229.578" Z="772.6265" />
    <Hotspot X="-4993.881" Y="-1367.222" Z="769.8398" />
    <Hotspot X="-4944.493" Y="-1495.737" Z="767.0601" />
    <Hotspot X="-4853.17" Y="-1583.252" Z="764.4482" />
    <Hotspot X="-4770.184" Y="-1638.366" Z="681.5156" />
    <Hotspot X="-4633.814" Y="-1657.437" Z="666.7637" />
    <Hotspot X="-4520.528" Y="-1641.838" Z="657.5465" />
    <Hotspot X="-4636.015" Y="-1689.417" Z="652.892" />
    <Hotspot X="-4774.834" Y="-1685.891" Z="655.5103" />
    <Hotspot X="-4912.543" Y="-1684.126" Z="668.6502" />
    <Hotspot X="-5048.174" Y="-1674.773" Z="658.16" />
    <Hotspot X="-5177.132" Y="-1636.497" Z="628.8606" />
    <Hotspot X="-5242.518" Y="-1526.117" Z="612.4319" />
    <Hotspot X="-5374.781" Y="-1561.224" Z="599.2106" />
    <Hotspot X="-5505.405" Y="-1593.654" Z="570.3266" />
    <Hotspot X="-5638.45" Y="-1626.031" Z="553.9111" />
    <Hotspot X="-5723.516" Y="-1587.986" Z="543.6496" />
    <Hotspot X="-5689.871" Y="-1453.929" Z="539.2948" />
    <Hotspot X="-5698.48" Y="-1315.813" Z="531.055" />
    <Hotspot X="-5723.704" Y="-1179.929" Z="521.7545" />
    <Hotspot X="-5749.039" Y="-1043.437" Z="512.4124" />
    <Hotspot X="-5774.29" Y="-907.0012" Z="503.8734" />
    <Hotspot X="-5799.155" Y="-769.9429" Z="512.2843" />
    <Hotspot X="-5823.854" Y="-633.9076" Z="520.7408" />
    <Hotspot X="-5848.656" Y="-498.0044" Z="527.6548" />
    <Hotspot X="-5872.693" Y="-361.7296" Z="529.2587" />
    <Hotspot X="-5897.269" Y="-225.4416" Z="522.2187" />
    <Hotspot X="-5930.264" Y="-91.09277" Z="514.7645" />
    <Hotspot X="-5936.938" Y="42.8125" Z="536.6978" />
    <Hotspot X="-5973.959" Y="166.8747" Z="552.2452" />
    <Hotspot X="-6038.938" Y="287.9911" Z="556.6213" />
    <Hotspot X="-6069.17" Y="380.2428" Z="560.7701" />
    <Hotspot X="-6072.25" Y="414.734" Z="556.6338" />
    <Hotspot X="-6030.002" Y="524.3483" Z="577.32" />
    <Hotspot X="-5909.156" Y="586.3564" Z="591.5592" />
    <Hotspot X="-5772.572" Y="577.5048" Z="586.8212" />
    <Hotspot X="-5640.45" Y="558.9954" Z="553.7578" />
    <Hotspot X="-5503.705" Y="568.9771" Z="541.8477" />
    <Hotspot X="-5366.056" Y="588.4393" Z="536.423" />
    <Hotspot X="-5229.134" Y="601.4133" Z="549.5311" />
    <Hotspot X="-5105.977" Y="639.7005" Z="557.269" />
    <Hotspot X="-5115.55" Y="535.5984" Z="539.9884" />
    <Hotspot X="-5249.505" Y="568.4352" Z="534.9942" />
    <Hotspot X="-5384.603" Y="565.8932" Z="529.3517" />
    <Hotspot X="-5324.904" Y="581.4375" Z="561.0107" />
    <Hotspot X="-5210.245" Y="640.2855" Z="564.1078" />
    <Hotspot X="-5102.487" Y="699.3882" Z="591.2917" />
    <Hotspot X="-5105.999" Y="634.3572" Z="555.4695" />
    <Hotspot X="-5183.896" Y="623.2424" Z="497.7786" />
    <Hotspot X="-5190.831" Y="619.7297" Z="488.6401" />
    <Hotspot X="-5144.42" Y="550.9495" Z="488.2163" />
    <Hotspot X="-5080.966" Y="428.9662" Z="497.8192" />
    <Hotspot X="-5049.716" Y="296.426" Z="518.3066" />
    <Hotspot X="-5027.139" Y="163.1699" Z="548.6416" />
    <Hotspot X="-5040.595" Y="32.97419" Z="552.7984" />
    <Hotspot X="-4972.415" Y="56.99432" Z="527.7863" />
    <Hotspot X="-5036.574" Y="73.28274" Z="524.9382" />
    <Hotspot X="-5068.845" Y="-58.46042" Z="532.5684" />
    <Hotspot X="-5107.013" Y="-191.1821" Z="544.51" />
    <Hotspot X="-5148.976" Y="-321.612" Z="564.8651" />
    <Hotspot X="-5189.905" Y="-448.8315" Z="584.7191" />
    <Hotspot X="-5231.962" Y="-579.5532" Z="605.1197" />
    <Hotspot X="-5250.289" Y="-713.9815" Z="625.4747" />
    <Hotspot X="-5198.41" Y="-813.189" Z="645.764" />
    <Hotspot X="-5061.473" Y="-822.4867" Z="666.1545" />
    <Hotspot X="-5013.804" Y="-853.459" Z="696.74" />
    <Hotspot X="-5030.288" Y="-863.2897" Z="693.0029" />
    <Hotspot X="-5009.991" Y="-933.8281" Z="724.9615" />
    <Hotspot X="-5111.008" Y="-1018.454" Z="698.1007" />
    <Hotspot X="-5174.75" Y="-1130.89" Z="651.8535" />
    <Hotspot X="-5273.539" Y="-1222.174" Z="617.9431" />
    <Hotspot X="-5351.079" Y="-1332.54" Z="588.9227" />
    <Hotspot X="-5458.642" Y="-1393.353" Z="566.5483" />
    <Hotspot X="-5528.564" Y="-1277.472" Z="544.4102" />
    <Hotspot X="-5596.549" Y="-1158.981" Z="530.3615" />
    <Hotspot X="-5691.539" Y="-1059.87" Z="512.9341" />
    <Hotspot X="-5741.916" Y="-933.7592" Z="509.0689" />
    <Hotspot X="-5741.468" Y="-797.4101" Z="533.2333" />
    <Hotspot X="-5719.027" Y="-664.2563" Z="564.2503" />
    <Hotspot X="-5681.942" Y="-557.1846" Z="566.225" />
    <Hotspot X="-5601.274" Y="-485.594" Z="533.2886" />
    <Hotspot X="-5507.977" Y="-386.5097" Z="518.4197" />
    <Hotspot X="-5432.061" Y="-272.0984" Z="505.4406" />
    <Hotspot X="-5391.684" Y="-140.3348" Z="503.5992" />
    <Hotspot X="-5353.89" Y="-8.121105" Z="515.3051" />
    <Hotspot X="-5304.193" Y="120.0792" Z="527.0372" />
    <Hotspot X="-5198.742" Y="104.5675" Z="538.7256" />
    <Hotspot X="-5198.37" Y="-25.56116" Z="550.0617" />
    <Hotspot X="-5237.73" Y="-157.8399" Z="552.1509" />
    <Hotspot X="-5279.613" Y="-289.8016" Z="552.2722" />
    <Hotspot X="-5305.327" Y="-425.3068" Z="547.6686" />
    <Hotspot X="-5202.552" Y="-430.8185" Z="556.5173" />
    <Hotspot X="-5097.656" Y="-367.3644" Z="583.3598" />
    <Hotspot X="-4956.414" Y="-287.2686" Z="612.0749" />
    <Hotspot X="-4839.384" Y="-339.0488" Z="610.7203" />
    <Hotspot X="-4779.128" Y="-453.0979" Z="643.6332" />
    <Hotspot X="-4725.677" Y="-577.0991" Z="669.2991" />
    <Hotspot X="-4633.392" Y="-675.2702" Z="659.5443" />
    <Hotspot X="-4543.371" Y="-653.6563" Z="567.0485" />
    <Hotspot X="-4459.351" Y="-653.8125" Z="456.9662" />
    <Hotspot X="-4376.146" Y="-695.2437" Z="359.0368" />
    <Hotspot X="-4417.008" Y="-674.5051" Z="405.7489" />
    <Hotspot X="-4501.09" Y="-651.9069" Z="511.7" />
    <Hotspot X="-4581.598" Y="-677.6387" Z="616.6793" />
    <Hotspot X="-4685.683" Y="-633.2836" Z="671.5236" />
    <Hotspot X="-4756.95" Y="-516.23" Z="660.4738" />
    <Hotspot X="-4796.729" Y="-391.5724" Z="617.743" />
    <Hotspot X="-4890.247" Y="-292.7223" Z="608.5934" />
    <Hotspot X="-5039.998" Y="-332.4856" Z="598.1144" />
    <Hotspot X="-5144.578" Y="-395.7481" Z="571.3529" />
    <Hotspot X="-5263.762" Y="-459.7911" Z="546.0945" />
    <Hotspot X="-5295.301" Y="-357.2826" Z="549.2288" />
    <Hotspot X="-5258.671" Y="-223.8208" Z="552.2115" />
    <Hotspot X="-5216.757" Y="-91.76061" Z="552.0903" />
    <Hotspot X="-5186.605" Y="42.20533" Z="544.2088" />
    <Hotspot X="-5246.212" Y="151.3263" Z="532.8785" />
    <Hotspot X="-5332.317" Y="57.44582" Z="521.2017" />
    <Hotspot X="-5369.142" Y="-75.54531" Z="509.4201" />
    <Hotspot X="-5413.602" Y="-205.5475" Z="498.9638" />
    <Hotspot X="-5465.572" Y="-331.9583" Z="511.9494" />
    <Hotspot X="-5550.077" Y="-440.643" Z="524.8641" />
    <Hotspot X="-5655.909" Y="-519.6011" Z="553.1154" />
    <Hotspot X="-5702.071" Y="-597.4526" Z="570.0093" />
    <Hotspot X="-5730.958" Y="-731.1033" Z="550.764" />
    <Hotspot X="-5745.082" Y="-864.9372" Z="518.695" />
    <Hotspot X="-5728.045" Y="-1000.601" Z="506.1034" />
    <Hotspot X="-5645.358" Y="-1110.07" Z="521.3669" />
    <Hotspot X="-5557.209" Y="-1215.549" Z="537.6747" />
    <Hotspot X="-5499.57" Y="-1339.576" Z="552.7396" />
    <Hotspot X="-5395.71" Y="-1383.54" Z="580.0921" />
    <Hotspot X="-5312.552" Y="-1275.93" Z="599.7999" />
    <Hotspot X="-5222.932" Y="-1177.983" Z="634.5936" />
    <Hotspot X="-5140.655" Y="-1074.99" Z="671.9713" />
    <Hotspot X="-5060.601" Y="-977.2517" Z="719.2646" />
    <Hotspot X="-5027.277" Y="-878.5264" Z="692.9358" />
    <Hotspot X="-5018.634" Y="-862.3019" Z="695.2868" />
    <Hotspot X="-5012.033" Y="-844.6788" Z="689.1975" />
    <Hotspot X="-5129.618" Y="-817.8598" Z="656.0074" />
    <Hotspot X="-5251.436" Y="-782.5248" Z="635.6624" />
    <Hotspot X="-5248.824" Y="-645.7287" Z="615.3326" />
    <Hotspot X="-5210.928" Y="-514.1761" Z="594.9169" />
    <Hotspot X="-5169.081" Y="-384.1029" Z="574.6175" />
    <Hotspot X="-5127.984" Y="-256.3646" Z="554.6825" />
    <Hotspot X="-5085.854" Y="-125.4155" Z="534.2487" />
    <Hotspot X="-5060.953" Y="10.08494" Z="529.9777" />
    <Hotspot X="-4985.788" Y="113.9816" Z="517.5444" />
    <Hotspot X="-5021.75" Y="12.91336" Z="540.8932" />
    <Hotspot X="-5028.346" Y="95.98184" Z="554.4328" />
    <Hotspot X="-5038.383" Y="229.5329" Z="533.5344" />
    <Hotspot X="-5061.438" Y="363.3166" Z="504.8697" />
    <Hotspot X="-5108.408" Y="492.5647" Z="493.0361" />
    <Hotspot X="-5181.215" Y="609.0308" Z="485.3616" />
    <Hotspot X="-5193.634" Y="624.1243" Z="492.2762" />
    <Hotspot X="-5160.321" Y="625.6752" Z="513.33" />
    <Hotspot X="-5070.548" Y="674.7784" Z="594.3797" />
    <Hotspot X="-5149.805" Y="672.2957" Z="570.7385" />
    <Hotspot X="-5270.441" Y="617.0519" Z="585.1776" />
    <Hotspot X="-5376.835" Y="543.5944" Z="535.3594" />
    <Hotspot X="-5317.713" Y="578.8611" Z="532.6859" />
    <Hotspot X="-5182.743" Y="549.3007" Z="537.544" />
    <Hotspot X="-5073.988" Y="581.6634" Z="547.8679" />
    <Hotspot X="-5169.674" Y="634.5946" Z="557.8513" />
    <Hotspot X="-5297.44" Y="597.7155" Z="540.317" />
    <Hotspot X="-5435.076" Y="578.4886" Z="536.7409" />
    <Hotspot X="-5571.479" Y="560.4628" Z="548.5185" />
    <Hotspot X="-5708.217" Y="564.4418" Z="564.7883" />
    <Hotspot X="-5839.988" Y="587.1462" Z="592.64" />
    <Hotspot X="-5972.323" Y="562.2632" Z="587.3411" />
    <Hotspot X="-6067.679" Y="469.7942" Z="563.6011" />
    <Hotspot X="-6063.473" Y="392.0525" Z="560.3007" />
    <Hotspot X="-6061.464" Y="353.6792" Z="559.161" />
    <Hotspot X="-6012.18" Y="224.5463" Z="557.6061" />
    <Hotspot X="-5936.12" Y="109.7181" Z="545.2115" />
    <Hotspot X="-5943.481" Y="-25.06569" Z="526.926" />
    <Hotspot X="-5913.086" Y="-158.0865" Z="516.8344" />
    <Hotspot X="-5883.958" Y="-293.2855" Z="526.2303" />
    <Hotspot X="-5860.521" Y="-429.608" Z="529.0121" />
    <Hotspot X="-5836.308" Y="-565.838" Z="524.9311" />
    <Hotspot X="-5811.394" Y="-702.5341" Z="516.4747" />
    <Hotspot X="-5786.659" Y="-838.7723" Z="508.0056" />
    <Hotspot X="-5761.669" Y="-975.3934" Z="507.7553" />
    <Hotspot X="-5736.346" Y="-1111.818" Z="517.0927" />
    <Hotspot X="-5711.086" Y="-1247.905" Z="526.4071" />
    <Hotspot X="-5689.671" Y="-1384.71" Z="535.5702" />
    <Hotspot X="-5702.533" Y="-1521.831" Z="542.1115" />
    <Hotspot X="-5704.777" Y="-1643.835" Z="547.7027" />
    <Hotspot X="-5572.667" Y="-1606.928" Z="560.0336" />
    <Hotspot X="-5439.865" Y="-1580.877" Z="587.2665" />
    <Hotspot X="-5309.849" Y="-1537.641" Z="608.4641" />
    <Hotspot X="-5213.412" Y="-1582.678" Z="615.4871" />
    <Hotspot X="-5112.898" Y="-1658.001" Z="642.0888" />
    <Hotspot X="-4982.066" Y="-1683.235" Z="675.2839" />
    <Hotspot X="-4843.74" Y="-1685.008" Z="662.0851" />
    <Hotspot X="-4705.622" Y="-1687.431" Z="653.4999" />
    <Hotspot X="-4566.72" Y="-1690.161" Z="652.8107" />
    <Hotspot X="-4568.898" Y="-1641.371" Z="662.1158" />
    <Hotspot X="-4702.558" Y="-1647.581" Z="671.4371" />
    <Hotspot X="-4821.353" Y="-1623.971" Z="724.489" />
    <Hotspot X="-4904.993" Y="-1551.513" Z="765.6702" />
    <Hotspot X="-4975.704" Y="-1433.847" Z="768.4514" />
    <Hotspot X="-5003.458" Y="-1299.579" Z="771.2214" />
    <Hotspot X="-4996.278" Y="-1161.054" Z="774.0135" />
    <Hotspot X="-4973.083" Y="-1024.449" Z="776.7961" />
    <Hotspot X="-4988.779" Y="-887.7314" Z="779.5724" />
    <Hotspot X="-4999.714" Y="-753.145" Z="782.3432" />
    <Hotspot X="-4981.002" Y="-620.5104" Z="760.7806" />
    <Hotspot X="-4961.374" Y="-494.2045" Z="705.7314" />
    <Hotspot X="-4941.882" Y="-368.7737" Z="651.0637" />
    <Hotspot X="-4920.157" Y="-240.9482" Z="602.9497" />
    <Hotspot X="-4894.388" Y="-106.3906" Z="589.275" />
    <Hotspot X="-4892.591" Y="31.58115" Z="579.5356" />
    <Hotspot X="-4900.602" Y="169.819" Z="577.6018" />
    <Hotspot X="-4894.472" Y="306.8409" Z="589.977" />
    <Hotspot X="-4867.333" Y="439.5536" Z="582.9531" />
    <Hotspot X="-4836.635" Y="569.0805" Z="546.0369" />
    <Hotspot X="-4816.194" Y="702.0155" Z="515.0666" />
    <Hotspot X="-4859.075" Y="832.8332" Z="512.4058" />
    <Hotspot X="-4951.528" Y="935.5619" Z="509.749" />
    <Hotspot X="-5058.421" Y="1023.316" Z="507.0895" />
    <Hotspot X="-5186.336" Y="1055.456" Z="525.3792" />
    <Hotspot X="-5319.999" Y="1025.484" Z="545.7863" />
    <Hotspot X="-5444.412" Y="967.2888" Z="560.1341" />
    <Hotspot X="-5567.107" Y="904.3233" Z="574.507" />
    <Hotspot X="-5690.076" Y="841.2171" Z="588.9119" />
    <Hotspot X="-5813.179" Y="777.4847" Z="600.4357" />
    <Hotspot X="-5937.496" Y="717.296" Z="600.0107" />
    <Hotspot X="-6072.387" Y="707.6163" Z="582.5109" />
    <Hotspot X="-6207.891" Y="715.0156" Z="563.1039" />
    <Hotspot X="-6261.063" Y="608.3832" Z="581.369" />
    <Hotspot X="-6257.861" Y="471.6058" Z="599.7661" />
    <Hotspot X="-6241.16" Y="335.6912" Z="615.2473" />
    <Hotspot X="-6160.343" Y="225.7057" Z="607.9044" />
    <Hotspot X="-6071.63" Y="119.0727" Z="600.5084" />
    <Hotspot X="-6024.837" Y="-10.70715" Z="593.1216" />
    <Hotspot X="-5987.378" Y="-143.6455" Z="585.7622" />
    <Hotspot X="-5949.732" Y="-277.2459" Z="578.3662" />
    <Hotspot X="-5912.367" Y="-409.8533" Z="571.0252" />
    <Hotspot X="-5874.693" Y="-543.553" Z="563.6238" />
    <Hotspot X="-5837.234" Y="-676.4915" Z="556.2644" />
    <Hotspot X="-5809.657" Y="-811.8981" Z="548.8996" />
    <Hotspot X="-5785.608" Y="-947.8857" Z="541.533" />
    <Hotspot X="-5792.049" Y="-1085.478" Z="534.1553" />
    <Hotspot X="-5812.374" Y="-1222.646" Z="526.7667" />
    <Hotspot X="-5824.909" Y="-1359.153" Z="519.4312" />
    <Hotspot X="-5783.878" Y="-1491.267" Z="512.0572" />
    <Hotspot X="-5744.403" Y="-1624.192" Z="507.5502" />
    <Hotspot X="-5715.448" Y="-1759.354" Z="516.4889" />
    <Hotspot X="-5686.427" Y="-1894.819" Z="525.4476" />
    <Hotspot X="-5657.45" Y="-2030.082" Z="534.3929" />
    <Hotspot X="-5625.714" Y="-2164.96" Z="547.2207" />
    <Hotspot X="-5554.114" Y="-2281.042" Z="562.1843" />
    <Hotspot X="-5447.894" Y="-2362.186" Z="574.7994" />
    <Hotspot X="-5319.918" Y="-2351.11" Z="588.3187" />
    <Hotspot X="-5182.323" Y="-2336.1" Z="575.4694" />
    <Hotspot X="-5045.633" Y="-2322.413" Z="586.1278" />
    <Hotspot X="-4916.011" Y="-2302.026" Z="612.4506" />
    <Hotspot X="-4833.812" Y="-2208.046" Z="652.2847" />
    <Hotspot X="-4740.043" Y="-2105.632" Z="663.8947" />
    <Hotspot X="-4652.188" Y="-1998.801" Z="675.3876" />
    <Hotspot X="-4597.665" Y="-1874.776" Z="661.4113" />
    <Hotspot X="-4553.322" Y="-1745.692" Z="639.6716" />
    <Hotspot X="-4461.672" Y="-1666.032" Z="596.6843" />
    <Hotspot X="-4408.46" Y="-1577.274" Z="620.7855" />
    <Hotspot X="-4509.094" Y="-1542.755" Z="668.3219" />
    <Hotspot X="-4577.566" Y="-1432.713" Z="715.6223" />
    <Hotspot X="-4632.927" Y="-1316.542" Z="762.3151" />
    <Hotspot X="-4657.201" Y="-1191.271" Z="805.8781" />
    <Hotspot X="-4682.088" Y="-1062.832" Z="850.5427" />
    <Hotspot X="-4692.361" Y="-929.059" Z="876.647" />
    <Hotspot X="-4720.448" Y="-807.3188" Z="818.1214" />
    <Hotspot X="-4748.852" Y="-684.9063" Z="760.3337" />
    <Hotspot X="-4779.456" Y="-559.045" Z="710.0926" />
    <Hotspot X="-4782.407" Y="-426.5312" Z="672.5021" />
    <Hotspot X="-4773.3" Y="-292.3785" Z="640.8404" />
    <Hotspot X="-4763.043" Y="-156.2607" Z="623.7338" />
    <Hotspot X="-4750.952" Y="-18.28223" Z="630.1443" />
    <Hotspot X="-4738.937" Y="118.8394" Z="636.5149" />
    <Hotspot X="-4726.875" Y="256.4751" Z="642.9094" />
    <Hotspot X="-4719.573" Y="393.8978" Z="635.4853" />
    <Hotspot X="-4718.372" Y="529.4171" Z="608.0354" />
    <Hotspot X="-4717.193" Y="666.1315" Z="584.5714" />
    <Hotspot X="-4754.75" Y="798.2262" Z="585.5403" />
    <Hotspot X="-4802.525" Y="928.1307" Z="586.5065" />
    <Hotspot X="-4847.84" Y="1058.413" Z="592.0004" />
    <Hotspot X="-4887.375" Y="1184.764" Z="628.5195" />
    <Hotspot X="-4896.361" Y="1309.394" Z="650.7657" />
    <Hotspot X="-4957.206" Y="1406.168" Z="619.631" />
    <Hotspot X="-5090.156" Y="1406.174" Z="588.5966" />
    <Hotspot X="-5174.548" Y="1304.631" Z="597.8949" />
    <Hotspot X="-5275.466" Y="1215.831" Z="564.645" />
    <Hotspot X="-5390.464" Y="1142.335" Z="550.6386" />
    <Hotspot X="-5515.008" Y="1084.479" Z="564.9509" />
    <Hotspot X="-5640.764" Y="1026.06" Z="579.4023" />
    <Hotspot X="-5765.494" Y="968.1179" Z="593.736" />
    <Hotspot X="-5889.313" Y="906.7559" Z="602.714" />
    <Hotspot X="-6021.016" Y="869.8518" Z="611.1099" />
    <Hotspot X="-6154.642" Y="857.7396" Z="577.9476" />
    <Hotspot X="-6288.482" Y="835.9409" Z="563.9802" />
    <Hotspot X="-6409.788" Y="772.4779" Z="567.11" />
    <Hotspot X="-6515.808" Y="691.945" Z="570.2704" />
    <Hotspot X="-6523.759" Y="553.9673" Z="573.4066" />
    <Hotspot X="-6457.179" Y="438.1901" Z="576.5536" />
    <Hotspot X="-6390.88" Y="318.0216" Z="580.3746" />
    <Hotspot X="-6302.365" Y="212.8151" Z="584.1717" />
    <Hotspot X="-6206.172" Y="113.3503" Z="587.674" />
    <Hotspot X="-6112.292" Y="12.16468" Z="596.2148" />
    <Hotspot X="-6078.399" Y="-115.0664" Z="565.3434" />
    <Hotspot X="-6060.745" Y="-252.2947" Z="553.634" />
    <Hotspot X="-6052.451" Y="-389.5428" Z="548.2513" />
    <Hotspot X="-6003.944" Y="-517.1409" Z="550.3069" />
    <Hotspot X="-5975.615" Y="-652.0032" Z="552.3544" />
    <Hotspot X="-5948.646" Y="-788.3109" Z="554.4157" />
    <Hotspot X="-5929.547" Y="-925.9864" Z="557.3" />
    <Hotspot X="-5940.97" Y="-1063.244" Z="551.4102" />
    <Hotspot X="-5923.506" Y="-1199.2" Z="541.088" />
    <Hotspot X="-5893.913" Y="-1332.73" Z="543.7009" />
    <Hotspot X="-5884.146" Y="-1470.598" Z="556.3707" />
    <Hotspot X="-5883.162" Y="-1608.27" Z="554.2932" />
    <Hotspot X="-5886.579" Y="-1747.298" Z="546.7953" />
    <Hotspot X="-5889.198" Y="-1885.07" Z="537.8654" />
    <Hotspot X="-5884.93" Y="-2024.37" Z="537.199" />
    <Hotspot X="-5797.63" Y="-2124.067" Z="547.879" />
    <Hotspot X="-5679.385" Y="-2192.996" Z="555.3704" />
    <Hotspot X="-5554.914" Y="-2247.492" Z="565.0845" />
  </Hotspots>
  <Blackspots>
  </Blackspots>
</HBProfile>
