<HBProfile>
  <Name></Name>
  <MinDurability>0.4</MinDurability>
  <MinFreeBagSlots>1</MinFreeBagSlots>
  
  <MinLevel>1</MinLevel>
  <MaxLevel>86</MaxLevel>
  <Factions>99999</Factions>
  
  <MailGrey>False</MailGrey>
  <MailWhite>True</MailWhite>
  <MailGreen>True</MailGreen>
  <MailBlue>True</MailBlue>
  <MailPurple>True</MailPurple>
 
  <SellGrey>True</SellGrey>
  <SellWhite>True</SellWhite>
  <SellGreen>False</SellGreen>
  <SellBlue>False</SellBlue>
  <SellPurple>False</SellPurple>

	<Vendors>

	</Vendors>
	
	<Mailboxes>

	</Mailboxes>

  <Hotspots>
    <Hotspot X="-8280.26" Y="965.5713" Z="403.7067" />
    <Hotspot X="-8174.291" Y="967.318" Z="356.865" />
    <Hotspot X="-8073.991" Y="947.3559" Z="281.6941" />
    <Hotspot X="-8017.359" Y="893.4828" Z="185.1661" />
    <Hotspot X="-8030.973" Y="781.7441" Z="128.7642" />
    <Hotspot X="-8056.228" Y="656.1281" Z="122.6149" />
    <Hotspot X="-8072.484" Y="530.1476" Z="117.4618" />
    <Hotspot X="-7991.993" Y="451.828" Z="118.0878" />
    <Hotspot X="-7919.873" Y="538.7051" Z="119.007" />
    <Hotspot X="-7900.76" Y="666.5173" Z="115.0085" />
    <Hotspot X="-7897.849" Y="794.6829" Z="108.2196" />
    <Hotspot X="-7897.216" Y="924.4421" Z="104.5502" />
    <Hotspot X="-7900.006" Y="1054.234" Z="102.0218" />
    <Hotspot X="-7905.422" Y="1182.586" Z="98.65859" />
    <Hotspot X="-7910.88" Y="1312.583" Z="96.92164" />
    <Hotspot X="-7916.045" Y="1442.94" Z="103.2452" />
    <Hotspot X="-7921.466" Y="1571.397" Z="112.3493" />
    <Hotspot X="-7927.501" Y="1698.666" Z="127.3643" />
    <Hotspot X="-7935.657" Y="1824.229" Z="153.2584" />
    <Hotspot X="-7902.456" Y="1907.644" Z="139.6408" />
    <Hotspot X="-7817.159" Y="1817.615" Z="133.2082" />
    <Hotspot X="-7798.576" Y="1690.758" Z="130.3562" />
    <Hotspot X="-7795.687" Y="1560.99" Z="128.5745" />
    <Hotspot X="-7793.287" Y="1432.258" Z="126.8898" />
    <Hotspot X="-7790.894" Y="1303.814" Z="125.2088" />
    <Hotspot X="-7788.5" Y="1175.401" Z="123.5283" />
    <Hotspot X="-7786.108" Y="1047.02" Z="121.8481" />
    <Hotspot X="-7783.701" Y="917.8732" Z="120.158" />
    <Hotspot X="-7781.3" Y="789.0456" Z="118.472" />
    <Hotspot X="-7785.248" Y="661.5627" Z="108.2245" />
    <Hotspot X="-7800.191" Y="535.5015" Z="83.82414" />
    <Hotspot X="-7811.649" Y="407.7315" Z="96.60307" />
    <Hotspot X="-7741.471" Y="303.7968" Z="110.1335" />
    <Hotspot X="-7645.71" Y="219.0711" Z="123.614" />
    <Hotspot X="-7550.7" Y="221.9605" Z="133.9791" />
    <Hotspot X="-7532.647" Y="351.4042" Z="131.2205" />
    <Hotspot X="-7519.909" Y="479.3879" Z="128.864" />
    <Hotspot X="-7533.692" Y="606.8249" Z="126.5116" />
    <Hotspot X="-7549.792" Y="735.33" Z="124.1387" />
    <Hotspot X="-7565.859" Y="863.5817" Z="121.7705" />
    <Hotspot X="-7575.401" Y="990.5834" Z="119.4228" />
    <Hotspot X="-7572.001" Y="1119.398" Z="117.0587" />
    <Hotspot X="-7566.833" Y="1247.559" Z="114.7086" />
    <Hotspot X="-7562.934" Y="1376.111" Z="112.3504" />
    <Hotspot X="-7595.042" Y="1498.141" Z="136.8885" />
    <Hotspot X="-7629.003" Y="1619.032" Z="164.9576" />
    <Hotspot X="-7662.98" Y="1739.984" Z="193.0407" />
    <Hotspot X="-7696.958" Y="1860.935" Z="221.1237" />
    <Hotspot X="-7725.238" Y="1982.72" Z="249.2695" />
    <Hotspot X="-7670.303" Y="2080.728" Z="277.7285" />
    <Hotspot X="-7549.154" Y="2048.551" Z="277.9249" />
    <Hotspot X="-7453.655" Y="1978.133" Z="239.2065" />
    <Hotspot X="-7444.873" Y="1858.562" Z="203.3904" />
    <Hotspot X="-7476.05" Y="1743.653" Z="158.7074" />
    <Hotspot X="-7523.758" Y="1624.868" Z="143.8972" />
    <Hotspot X="-7565.419" Y="1503.088" Z="136.4772" />
    <Hotspot X="-7577.671" Y="1375.733" Z="134.6725" />
    <Hotspot X="-7576.732" Y="1246.838" Z="136.8486" />
    <Hotspot X="-7588.419" Y="1119.234" Z="140.5405" />
    <Hotspot X="-7568.676" Y="992.2277" Z="144.2525" />
    <Hotspot X="-7546.233" Y="865.2285" Z="147.9683" />
    <Hotspot X="-7523.956" Y="739.1718" Z="151.6565" />
    <Hotspot X="-7501.776" Y="611.762" Z="155.3833" />
    <Hotspot X="-7543.027" Y="493.2592" Z="153.8313" />
    <Hotspot X="-7573.442" Y="368.9178" Z="160.1501" />
    <Hotspot X="-7582.317" Y="239.6714" Z="156.7585" />
    <Hotspot X="-7582.249" Y="212.4301" Z="156.5808" />
    <Hotspot X="-7508.226" Y="237.32" Z="152.4657" />
    <Hotspot X="-7389.84" Y="288.283" Z="144.9275" />
    <Hotspot X="-7265.91" Y="322.517" Z="145.7645" />
    <Hotspot X="-7169.837" Y="383.9541" Z="147.7913" />
    <Hotspot X="-7196.026" Y="510.3607" Z="144.9151" />
    <Hotspot X="-7218.484" Y="637.6978" Z="136.9195" />
    <Hotspot X="-7216.395" Y="766.3229" Z="129.7405" />
    <Hotspot X="-7237.47" Y="893.1956" Z="130.6651" />
    <Hotspot X="-7264.973" Y="1019.646" Z="133.3766" />
    <Hotspot X="-7292.287" Y="1145.224" Z="136.0693" />
    <Hotspot X="-7306.011" Y="1272.018" Z="147.3715" />
    <Hotspot X="-7313.365" Y="1400.697" Z="152.6369" />
    <Hotspot X="-7315.719" Y="1529.013" Z="148.6587" />
    <Hotspot X="-7305.07" Y="1653.312" Z="127.7758" />
    <Hotspot X="-7243.459" Y="1754.955" Z="117.4869" />
    <Hotspot X="-7123.112" Y="1778.101" Z="120.1763" />
    <Hotspot X="-7081.638" Y="1663.13" Z="126.2996" />
    <Hotspot X="-7086.152" Y="1536.488" Z="130.019" />
    <Hotspot X="-7127.483" Y="1415.109" Z="133.7201" />
    <Hotspot X="-7102.863" Y="1289.416" Z="137.4386" />
    <Hotspot X="-7029.38" Y="1185.913" Z="141.1378" />
    <Hotspot X="-6981.911" Y="1069.991" Z="144.8517" />
    <Hotspot X="-6982.142" Y="940.7975" Z="148.5877" />
    <Hotspot X="-6987.233" Y="811.9948" Z="152.3017" />
    <Hotspot X="-7002.894" Y="684.6415" Z="156.022" />
    <Hotspot X="-7038.179" Y="560.7611" Z="159.7332" />
    <Hotspot X="-7092.777" Y="444.4686" Z="163.4398" />
    <Hotspot X="-7098.489" Y="318.1967" Z="167.1592" />
    <Hotspot X="-6993.481" Y="268.9651" Z="170.875" />
    <Hotspot X="-6942.914" Y="381.9539" Z="170.4859" />
    <Hotspot X="-6946.649" Y="510.4449" Z="167.5644" />
    <Hotspot X="-6954.635" Y="639.4775" Z="164.8571" />
    <Hotspot X="-6954.497" Y="766.769" Z="159.6847" />
    <Hotspot X="-6922.92" Y="891.368" Z="150.8728" />
    <Hotspot X="-6885.213" Y="1014.482" Z="145.8323" />
    <Hotspot X="-6856.485" Y="1139.329" Z="138.8546" />
    <Hotspot X="-6843.289" Y="1266.841" Z="130.7901" />
    <Hotspot X="-6830.04" Y="1394.86" Z="122.6936" />
    <Hotspot X="-6814.446" Y="1523.293" Z="116.6422" />
    <Hotspot X="-6780.723" Y="1647.985" Z="127.4898" />
    <Hotspot X="-6747.249" Y="1771.757" Z="138.2573" />
    <Hotspot X="-6681.282" Y="1879.128" Z="149.0461" />
    <Hotspot X="-6563.625" Y="1876.196" Z="147.6237" />
    <Hotspot X="-6441.68" Y="1835.428" Z="147.9053" />
    <Hotspot X="-6320.96" Y="1797.205" Z="149.5932" />
    <Hotspot X="-6301.886" Y="1681.765" Z="151.289" />
    <Hotspot X="-6338.236" Y="1558.39" Z="152.9786" />
    <Hotspot X="-6438.582" Y="1484.736" Z="154.6636" />
    <Hotspot X="-6561.643" Y="1475.146" Z="156.3474" />
    <Hotspot X="-6620.743" Y="1359.896" Z="158.0437" />
    <Hotspot X="-6679.45" Y="1245.412" Z="159.7287" />
    <Hotspot X="-6719.675" Y="1123.472" Z="161.4216" />
    <Hotspot X="-6762.986" Y="1002.765" Z="165.1821" />
    <Hotspot X="-6814.147" Y="884.8666" Z="168.885" />
    <Hotspot X="-6849.741" Y="764.5316" Z="172.5833" />
    <Hotspot X="-6828.104" Y="636.8422" Z="176.3147" />
    <Hotspot X="-6819.708" Y="508.6596" Z="180.0221" />
    <Hotspot X="-6815.682" Y="379.5957" Z="183.7425" />
    <Hotspot X="-6819.901" Y="251.4647" Z="187.4518" />
    <Hotspot X="-6841.293" Y="124.349" Z="191.1658" />
    <Hotspot X="-6796.291" Y="19.95019" Z="159.7206" />
    <Hotspot X="-6684.874" Y="47.45977" Z="172.4591" />
    <Hotspot X="-6594.041" Y="136.8334" Z="192.0345" />
    <Hotspot X="-6485.396" Y="137.1141" Z="179.0751" />
    <Hotspot X="-6409.121" Y="234.3569" Z="156.4488" />
    <Hotspot X="-6352.056" Y="347.3514" Z="137.2539" />
    <Hotspot X="-6298.818" Y="465.1834" Z="135.9006" />
    <Hotspot X="-6270.274" Y="587.4198" Z="134.5562" />
    <Hotspot X="-6289.889" Y="715.6923" Z="129.5881" />
    <Hotspot X="-6304.549" Y="843.3215" Z="121.9552" />
    <Hotspot X="-6307.889" Y="971.4832" Z="116.5682" />
    <Hotspot X="-6305.633" Y="1099.803" Z="118.1616" />
    <Hotspot X="-6299.512" Y="1228.93" Z="123.2415" />
    <Hotspot X="-6293.394" Y="1357.993" Z="128.3188" />
    <Hotspot X="-6311.82" Y="1471.394" Z="136.2445" />
    <Hotspot X="-6408.837" Y="1428.489" Z="136.26" />
    <Hotspot X="-6433.074" Y="1302.344" Z="131.0763" />
    <Hotspot X="-6450.187" Y="1175.358" Z="124.0522" />
    <Hotspot X="-6521.681" Y="1068.879" Z="133.4488" />
    <Hotspot X="-6614.222" Y="981.0081" Z="145.2214" />
    <Hotspot X="-6705.876" Y="894.0525" Z="173.7695" />
    <Hotspot X="-6797.842" Y="806.1085" Z="168.1532" />
    <Hotspot X="-6843.143" Y="696.6274" Z="132.1683" />
    <Hotspot X="-6839.387" Y="627.3212" Z="128.6591" />
    <Hotspot X="-6819.167" Y="501.0381" Z="131.8533" />
    <Hotspot X="-6784.825" Y="377.7671" Z="128.9152" />
    <Hotspot X="-6747.586" Y="254.8042" Z="128.8322" />
    <Hotspot X="-6710.328" Y="132.3145" Z="128.8329" />
    <Hotspot X="-6657.104" Y="16.55088" Z="128.039" />
    <Hotspot X="-6572.133" Y="-79.15929" Z="122.6068" />
    <Hotspot X="-6483.241" Y="-171.3291" Z="121.6254" />
    <Hotspot X="-6408.395" Y="-254.2813" Z="123.9665" />
    <Hotspot X="-6322.225" Y="-348.8279" Z="121.9425" />
    <Hotspot X="-6224.204" Y="-380.9459" Z="143.4592" />
    <Hotspot X="-6168.478" Y="-281.6784" Z="203.606" />
    <Hotspot X="-6156.025" Y="-160.6239" Z="245.9118" />
    <Hotspot X="-6138.51" Y="-36.83509" Z="276.6879" />
    <Hotspot X="-6120.121" Y="89.05718" Z="294.3342" />
    <Hotspot X="-6113.552" Y="218.0766" Z="289.9787" />
    <Hotspot X="-6111.109" Y="295.3917" Z="281.0622" />
    <Hotspot X="-6111.606" Y="282.827" Z="282.3505" />
    <Hotspot X="-6116.918" Y="153.4021" Z="295.1497" />
    <Hotspot X="-6127.618" Y="25.37211" Z="287.5839" />
    <Hotspot X="-6148.725" Y="-99.03548" Z="262.3971" />
    <Hotspot X="-6162.583" Y="-221.7206" Z="225.4716" />
    <Hotspot X="-6191.027" Y="-334.5412" Z="174.7026" />
    <Hotspot X="-6277.454" Y="-394.1956" Z="117.4466" />
    <Hotspot X="-6365.402" Y="-301.9296" Z="125.3112" />
    <Hotspot X="-6440.398" Y="-218.8116" Z="122.9655" />
    <Hotspot X="-6526.11" Y="-124.1297" Z="120.3321" />
    <Hotspot X="-6616.515" Y="-33.44732" Z="126.2232" />
    <Hotspot X="-6689.162" Y="71.90006" Z="128.6062" />
    <Hotspot X="-6729.034" Y="193.5861" Z="128.8325" />
    <Hotspot X="-6766.269" Y="316.45" Z="128.8318" />
    <Hotspot X="-6803.141" Y="439.071" Z="130.4198" />
    <Hotspot X="-6832.173" Y="563.6381" Z="130.96" />
    <Hotspot X="-6842.716" Y="674.5978" Z="129.3263" />
    <Hotspot X="-6833.565" Y="758.9961" Z="143.8813" />
    <Hotspot X="-6753.23" Y="850.0298" Z="174.5377" />
    <Hotspot X="-6660.445" Y="937.0318" Z="159.4456" />
    <Hotspot X="-6565.873" Y="1023.249" Z="138.4085" />
    <Hotspot X="-6481.522" Y="1118.889" Z="128.2316" />
    <Hotspot X="-6438.138" Y="1237.979" Z="126.0594" />
    <Hotspot X="-6424.104" Y="1365.994" Z="133.7163" />
    <Hotspot X="-6373.235" Y="1481.22" Z="139.5844" />
    <Hotspot X="-6290.369" Y="1421.808" Z="130.8293" />
    <Hotspot X="-6296.457" Y="1293.382" Z="125.777" />
    <Hotspot X="-6302.575" Y="1164.319" Z="120.6997" />
    <Hotspot X="-6308.657" Y="1036.02" Z="115.6524" />
    <Hotspot X="-6306.707" Y="907.2299" Z="118.1306" />
    <Hotspot X="-6299.738" Y="778.9052" Z="124.4571" />
    <Hotspot X="-6277.923" Y="651.8329" Z="132.359" />
    <Hotspot X="-6272.397" Y="523.8533" Z="135.2271" />
    <Hotspot X="-6325.247" Y="406.6892" Z="136.5724" />
    <Hotspot X="-6380.176" Y="289.6384" Z="142.8661" />
    <Hotspot X="-6439.934" Y="179.1275" Z="169.9299" />
    <Hotspot X="-6543.03" Y="158.9441" Z="196.2221" />
    <Hotspot X="-6639.608" Y="91.99867" Z="182.2521" />
    <Hotspot X="-6735.763" Y="9.205588" Z="161.652" />
    <Hotspot X="-6837.135" Y="65.76882" Z="176.3289" />
    <Hotspot X="-6830.576" Y="188.0327" Z="189.3051" />
    <Hotspot X="-6813.686" Y="315.6219" Z="185.5866" />
    <Hotspot X="-6817.681" Y="443.6652" Z="181.8957" />
    <Hotspot X="-6821.719" Y="573.1118" Z="178.1643" />
    <Hotspot X="-6838.877" Y="700.4194" Z="174.4568" />
    <Hotspot X="-6839.664" Y="826.0637" Z="170.7318" />
    <Hotspot X="-6788.567" Y="943.8158" Z="167.0336" />
    <Hotspot X="-6737.352" Y="1062.135" Z="163.1956" />
    <Hotspot X="-6705.059" Y="1185.577" Z="160.586" />
    <Hotspot X="-6650.351" Y="1302.157" Z="158.8935" />
    <Hotspot X="-6591.396" Y="1417.124" Z="157.2014" />
    <Hotspot X="-6502.511" Y="1488.599" Z="155.5084" />
    <Hotspot X="-6380.22" Y="1509.811" Z="153.8259" />
    <Hotspot X="-6318.064" Y="1619.025" Z="152.1376" />
    <Hotspot X="-6288.824" Y="1745.014" Z="150.4392" />
    <Hotspot X="-6378.836" Y="1825.396" Z="148.7442" />
    <Hotspot X="-6502.979" Y="1854.618" Z="147.0621" />
    <Hotspot X="-6622.143" Y="1901.016" Z="154.4579" />
    <Hotspot X="-6722.246" Y="1830.629" Z="143.6798" />
    <Hotspot X="-6763.949" Y="1710.009" Z="132.8856" />
    <Hotspot X="-6797.564" Y="1585.716" Z="122.0727" />
    <Hotspot X="-6823.307" Y="1459.915" Z="118.5792" />
    <Hotspot X="-6836.727" Y="1330.248" Z="126.78" />
    <Hotspot X="-6849.89" Y="1203.054" Z="134.8244" />
    <Hotspot X="-6865.336" Y="1075.434" Z="142.9229" />
    <Hotspot X="-6904.136" Y="953.0643" Z="148.3393" />
    <Hotspot X="-6941.612" Y="829.9769" Z="153.3939" />
    <Hotspot X="-6958.575" Y="703.1498" Z="163.5212" />
    <Hotspot X="-6950.659" Y="575.2319" Z="166.2051" />
    <Hotspot X="-6942.681" Y="446.3267" Z="168.9097" />
    <Hotspot X="-6957.959" Y="320.0222" Z="172.7338" />
    <Hotspot X="-7054.02" Y="275.5989" Z="169.03" />
    <Hotspot X="-7104.105" Y="382.1716" Z="165.3059" />
    <Hotspot X="-7064.644" Y="501.7462" Z="161.6012" />
    <Hotspot X="-7020.672" Y="622.2256" Z="157.8918" />
    <Hotspot X="-6989.776" Y="747.6572" Z="154.1568" />
    <Hotspot X="-6984.686" Y="876.428" Z="150.4438" />
    <Hotspot X="-6979.559" Y="1006.155" Z="146.7032" />
    <Hotspot X="-6994.5" Y="1132.583" Z="143.0122" />
    <Hotspot X="-7072.582" Y="1232.966" Z="139.2974" />
    <Hotspot X="-7119.103" Y="1351.066" Z="135.5908" />
    <Hotspot X="-7107.845" Y="1475.83" Z="131.8751" />
    <Hotspot X="-7074.123" Y="1598.636" Z="128.1703" />
    <Hotspot X="-7089.145" Y="1726.369" Z="124.4213" />
    <Hotspot X="-7186.093" Y="1783.303" Z="117.179" />
    <Hotspot X="-7291.729" Y="1712.218" Z="116.4738" />
    <Hotspot X="-7310.797" Y="1593.292" Z="147.4775" />
    <Hotspot X="-7316.014" Y="1464.668" Z="150.4574" />
    <Hotspot X="-7310.699" Y="1336.311" Z="154.8306" />
    <Hotspot X="-7301.4" Y="1208.801" Z="140.0372" />
    <Hotspot X="-7278.565" Y="1082.139" Z="134.7166" />
    <Hotspot X="-7251.035" Y="955.5634" Z="132.0024" />
    <Hotspot X="-7223.803" Y="830.36" Z="129.3177" />
    <Hotspot X="-7216.612" Y="701.5691" Z="134.7443" />
    <Hotspot X="-7207.768" Y="573.8909" Z="140.8508" />
    <Hotspot X="-7184.106" Y="447.0002" Z="148.8135" />
    <Hotspot X="-7201.755" Y="334.1273" Z="146.7902" />
    <Hotspot X="-7328.534" Y="308.7629" Z="144.8257" />
    <Hotspot X="-7449.12" Y="263.8246" Z="146.8613" />
    <Hotspot X="-7568.051" Y="216.0652" Z="155.7243" />
    <Hotspot X="-7583.493" Y="222.5446" Z="156.3091" />
    <Hotspot X="-7577.879" Y="304.2946" Z="158.4543" />
    <Hotspot X="-7563.911" Y="432.2599" Z="159.4755" />
    <Hotspot X="-7515.447" Y="551.4017" Z="155.2418" />
    <Hotspot X="-7512.707" Y="675.515" Z="153.519" />
    <Hotspot X="-7535.139" Y="802.4515" Z="149.8051" />
    <Hotspot X="-7557.532" Y="929.168" Z="146.0976" />
    <Hotspot X="-7579.781" Y="1055.068" Z="142.414" />
    <Hotspot X="-7582.564" Y="1183.163" Z="138.6908" />
    <Hotspot X="-7575.191" Y="1310.924" Z="135.5219" />
    <Hotspot X="-7575.652" Y="1439.557" Z="134.7244" />
    <Hotspot X="-7547.61" Y="1565.273" Z="138.721" />
    <Hotspot X="-7500.146" Y="1683.657" Z="151.2271" />
    <Hotspot X="-7458.013" Y="1802.131" Z="177.0467" />
    <Hotspot X="-7437.763" Y="1919.722" Z="221.5269" />
    <Hotspot X="-7493.211" Y="2023.706" Z="259.3427" />
    <Hotspot X="-7608.183" Y="2070.606" Z="290.1993" />
    <Hotspot X="-7715.662" Y="2044.974" Z="263.4328" />
    <Hotspot X="-7713.883" Y="1921.185" Z="235.113" />
    <Hotspot X="-7679.939" Y="1800.354" Z="207.0578" />
    <Hotspot X="-7645.979" Y="1679.463" Z="178.9887" />
    <Hotspot X="-7611.968" Y="1558.392" Z="150.8778" />
    <Hotspot X="-7577.915" Y="1437.171" Z="122.7321" />
    <Hotspot X="-7564.248" Y="1311.687" Z="113.5327" />
    <Hotspot X="-7569.409" Y="1183.686" Z="115.8799" />
    <Hotspot X="-7574.583" Y="1055.366" Z="118.2329" />
    <Hotspot X="-7565.268" Y="927.2559" Z="120.5999" />
    <Hotspot X="-7557.881" Y="799.8992" Z="122.9464" />
    <Hotspot X="-7541.833" Y="671.8058" Z="125.3117" />
    <Hotspot X="-7525.773" Y="543.6174" Z="127.6787" />
    <Hotspot X="-7526.281" Y="415.3643" Z="130.0428" />
    <Hotspot X="-7539.328" Y="286.8037" Z="132.4104" />
    <Hotspot X="-7585.053" Y="205.6645" Z="130.3642" />
    <Hotspot X="-7695.558" Y="259.2135" Z="116.8604" />
    <Hotspot X="-7787.098" Y="349.0729" Z="103.37" />
    <Hotspot X="-7806.148" Y="471.9153" Z="89.82616" />
    <Hotspot X="-7792.8" Y="598.3027" Z="95.55239" />
    <Hotspot X="-7780.099" Y="724.5839" Z="117.6284" />
    <Hotspot X="-7782.514" Y="854.1774" Z="119.3244" />
    <Hotspot X="-7784.911" Y="982.7816" Z="121.0074" />
    <Hotspot X="-7787.313" Y="1111.673" Z="122.6943" />
    <Hotspot X="-7789.702" Y="1239.863" Z="124.3719" />
    <Hotspot X="-7792.099" Y="1368.499" Z="126.0554" />
    <Hotspot X="-7794.484" Y="1496.465" Z="127.7301" />
    <Hotspot X="-7796.885" Y="1625.292" Z="129.416" />
    <Hotspot X="-7804.406" Y="1754.572" Z="131.6981" />
    <Hotspot X="-7850.517" Y="1872.507" Z="135.6658" />
    <Hotspot X="-7955.081" Y="1883.144" Z="143.9736" />
    <Hotspot X="-7931.15" Y="1761.63" Z="140.7704" />
    <Hotspot X="-7924.177" Y="1635.625" Z="116.9014" />
    <Hotspot X="-7918.763" Y="1507.328" Z="107.8085" />
    <Hotspot X="-7913.3" Y="1377.885" Z="98.63456" />
    <Hotspot X="-7908.15" Y="1247.208" Z="96.96587" />
    <Hotspot X="-7902.717" Y="1118.474" Z="100.3385" />
    <Hotspot X="-7897.321" Y="989.0358" Z="103.717" />
    <Hotspot X="-7897.536" Y="859.9524" Z="105.9912" />
    <Hotspot X="-7898.169" Y="730.7736" Z="110.7939" />
    <Hotspot X="-7909.135" Y="602.8168" Z="117.6802" />
    <Hotspot X="-7935.874" Y="477.2549" Z="119.5368" />
    <Hotspot X="-8051.472" Y="472.7984" Z="117.7504" />
    <Hotspot X="-8062.414" Y="592.7748" Z="117.0524" />
    <Hotspot X="-8042.236" Y="719.0854" Z="125.5521" />
    <Hotspot X="-8021.451" Y="841.8964" Z="147.8562" />
    <Hotspot X="-8036.832" Y="929.3852" Z="232.8972" />
    <Hotspot X="-8118.71" Y="957.1257" Z="325.8942" />
    <Hotspot X="-8232.184" Y="979.2062" Z="381.2143" />
  </Hotspots>
  <Blackspots>
  </Blackspots>
</HBProfile>
